pyzutil/__init__.py
pyzutil/libpyzutil.so
pyzutil/maps.py
pyzutil-0.0.1.post2.dist-info/LICENSE
pyzutil-0.0.1.post2.dist-info/METADATA
pyzutil-0.0.1.post2.dist-info/WHEEL
pyzutil-0.0.1.post2.dist-info/top_level.txt
pyzutil-0.0.1.post2.dist-info/RECORD
