Metadata-Version: 2.1
Name: pyzutil
Version: 0.0.1.post2
Summary: z/OS utilities for Python
Home-page: https://github.com/daveyc/pyzutil
Maintainer: David Crayford
Maintainer-email: dcrayford@gmail.com
License: MIT
Platform: any
Platform: none
Requires-Python: >=3.9
License-File: LICENSE
